BYTEX2_back.cpython-314-x86_64-linux-gnu.so
UnQL/Frontend.py
UnQL/UnQL.py
UnQL/__init__.py
UnQL/backend/__init__.py
UnQL/backend/back.py
UnitVerge/__init__.py
UnitVerge/Bytex/__init__.py
UnitVerge/Bytex/bx1/__executor.py
UnitVerge/Bytex/bx1/__init__.py
UnitVerge/Bytex/bx1/__vm.py
UnitVerge/Bytex/bx1/_lang.py
UnitVerge/Bytex/bx1/_tests.py
UnitVerge/Bytex/bx1dot9/__init__.py
UnitVerge/Bytex/bx1dot9/_parse_system/__init__.py
UnitVerge/Bytex/bx1dot9/_parse_system/_parse.py
UnitVerge/Bytex/bx1dot9/_parse_system/syntax.py
UnitVerge/Bytex/bx1dot9/_syntax_analyzer/__init__.py
UnitVerge/Bytex/bx1dot9/_syntax_analyzer/analyzer.py
UnitVerge/Bytex/bx2/__init__.py
UnitVerge/Bytex/bx2/builder.py
UnitVerge/Bytex/bx2/machine/BYTEX2_back.c
UnitVerge/Bytex/bx2/machine/__init__.py
UnitVerge/Bytex/bx2/translator/__init__.py
UnitVerge/Bytex/bx2/translator/basics.py
UnitVerge/Bytex/bx2/translator/exceptions.py
UnitVerge/Bytex/bx2/translator/generator.py
UnitVerge/Bytex/bx2/translator/translator.py
UnitVerge/Verge/__init__.py
UnitVerge/Verge/stdlib.py
UnitVerge/Verge/verge.py
UnitVerge/Verge/Basics/__init__.py
UnitVerge/Verge/Basics/syntax.py
UnitVerge/Verge/Basics/unit.py
UnitVerge/Verge/Basics/_base/__init__.py
UnitVerge/Verge/Basics/_base/exceptions.py
UnitVerge/Verge/Basics/_base/logger.py
UnitVerge/Verge/Basics/_base/uvobj.py
btx_tool/__init__.py
btx_tool/btx2.py
btx_tool/bytex.py
unitverge-1.4.dist-info/licenses/LICENSE
unitverge-1.4.dist-info/METADATA
unitverge-1.4.dist-info/WHEEL
unitverge-1.4.dist-info/entry_points.txt
unitverge-1.4.dist-info/top_level.txt
unitverge-1.4.dist-info/RECORD
